deephaven_enterprise/client/__init__.py
deephaven_enterprise/client/auth.py
deephaven_enterprise/client/controller.py
deephaven_enterprise/client/generate_scheduling.py
deephaven_enterprise/client/session_manager.py
deephaven_enterprise/client/util.py
deephaven_enterprise/proto/acl_pb2.py
deephaven_enterprise/proto/acl_pb2_grpc.py
deephaven_enterprise/proto/auth_pb2.py
deephaven_enterprise/proto/auth_pb2_grpc.py
deephaven_enterprise/proto/auth_service_pb2.py
deephaven_enterprise/proto/auth_service_pb2_grpc.py
deephaven_enterprise/proto/common_pb2.py
deephaven_enterprise/proto/common_pb2_grpc.py
deephaven_enterprise/proto/controller_common_pb2.py
deephaven_enterprise/proto/controller_common_pb2_grpc.py
deephaven_enterprise/proto/controller_pb2.py
deephaven_enterprise/proto/controller_pb2_grpc.py
deephaven_enterprise/proto/controller_service_pb2.py
deephaven_enterprise/proto/controller_service_pb2_grpc.py
deephaven_enterprise/proto/persistent_query_pb2.py
deephaven_enterprise/proto/persistent_query_pb2_grpc.py
deephaven_enterprise/proto/table_definition_pb2.py
deephaven_enterprise/proto/table_definition_pb2_grpc.py
deephaven_coreplus_client-1.20240517.547.dist-info/METADATA
deephaven_coreplus_client-1.20240517.547.dist-info/WHEEL
deephaven_coreplus_client-1.20240517.547.dist-info/top_level.txt
deephaven_coreplus_client-1.20240517.547.dist-info/RECORD
