Metadata-Version: 2.4
Name: deephaven-coreplus-client
Version: 1.20240517.547
Summary: The Deephaven Enterprise Core+ Python Client
Home-page: https://deephaven.io/
Author: Deephaven Data Labs
Author-email: python@deephaven.io
License: Deephaven Enterprise License Agreement
Classifier: Development Status :: 4 - Beta
Classifier: Intended Audience :: Developers
Classifier: License :: Other/Proprietary License
Classifier: Programming Language :: Python
Classifier: Programming Language :: Python :: 3
Classifier: Programming Language :: Python :: 3 :: Only
Classifier: Programming Language :: Python :: 3.9
Classifier: Programming Language :: Python :: 3.10
Classifier: Programming Language :: Python :: 3.11
Requires-Python: >=3.9
Requires-Dist: pydeephaven==0.40.7
Requires-Dist: pycryptodomex>=3.19.0
Requires-Dist: pycryptodome>=3.19.0
Requires-Dist: grpcio>=1.63.0
Requires-Dist: urllib3
Requires-Dist: requests
Dynamic: author
Dynamic: author-email
Dynamic: classifier
Dynamic: description
Dynamic: description-content-type
Dynamic: home-page
Dynamic: license
Dynamic: requires-dist
Dynamic: requires-python
Dynamic: summary
